sefi/__init__.py
sefi-2.2.6.dist-info/METADATA
sefi-2.2.6.dist-info/WHEEL
sefi-2.2.6.dist-info/RECORD
