Metadata-Version: 2.4
Name: sefi
Version: 2.2.6
Summary: Alias package for S3Fit (Simultaneous Spectrum and photometric-SED Fitting code for observation of galaxies)
Project-URL: Homepage, https://github.com/xychcz
Project-URL: Repository, https://github.com/xychcz/S3Fit
Project-URL: Documentation, https://github.com/xychcz/S3Fit/tree/main/manuals
Project-URL: Changelog, https://github.com/xychcz/S3Fit/releases
Author-email: Xiaoyang Chen <s3fit@xychen.me>
License-Expression: GPL-3.0-or-later
Keywords: SED fitting,astronomy,galaxy,spectral fitting
Classifier: Development Status :: 5 - Production/Stable
Classifier: Programming Language :: Python :: 3.10
Classifier: Topic :: Scientific/Engineering :: Astronomy
Requires-Python: >=3.10
Requires-Dist: s3fit>=2.2.4
Provides-Extra: pyneb
Requires-Dist: pyneb>=1.1.23; extra == 'pyneb'
